{
  "project_info": {
    "project_number": "569357099758",
    "firebase_url": "https://owhs-b725d-default-rtdb.firebaseio.com",
    "project_id": "owhs-b725d",
    "storage_bucket": "owhs-b725d.appspot.com"
  },
  "client": [
    {
      "client_info": {
        "mobilesdk_app_id": "1:569357099758:android:b79c9826c86adcd00d89ff",
        "android_client_info": {
          "package_name": "com.example.owhsapp"
        }
      },
      "oauth_client": [
        {
          "client_id": "569357099758-iuutpcfsp9arttaqds3sfogmnf1mc14a.apps.googleusercontent.com",
          "client_type": 3
        }
      ],
      "api_key": [
        {
          "current_key": "AIzaSyCiHMHCWTA8Fok5eL8GNba-4q3bMyeNT1U"
        }
      ],
      "services": {
        "appinvite_service": {
          "other_platform_oauth_client": [
            {
              "client_id": "569357099758-iuutpcfsp9arttaqds3sfogmnf1mc14a.apps.googleusercontent.com",
              "client_type": 3
            },
            {
              "client_id": "569357099758-lfsiktrcfif6p8ga9k73l0ss8f51o4v2.apps.googleusercontent.com",
              "client_type": 2,
              "ios_info": {
                "bundle_id": "com.example.owhsapp.RunnerTests"
              }
            }
          ]
        }
      }
    }
  ],
  "configuration_version": "1"
}